docscraper/__init__.py
docscraper/async_scraper.py
docscraper/cli.py
docscraper/crawler.py
docscraper/scraper.py
docscraper/utils.py
docscraperforai-0.1.0.dist-info/licenses/LICENSE
docscraperforai-0.1.0.dist-info/METADATA
docscraperforai-0.1.0.dist-info/WHEEL
docscraperforai-0.1.0.dist-info/top_level.txt
docscraperforai-0.1.0.dist-info/RECORD
